wunsen/__init__.py
wunsen/main.py
wunsen/japanese/__init__.py
wunsen/japanese/ja_mapping.py
wunsen/japanese/ja_thapsap.py
wunsen/korean/__init__.py
wunsen/korean/ko_mapping.py
wunsen/korean/ko_thapsap.py
wunsen/mandarin/__init__.py
wunsen/mandarin/zh_mapping.py
wunsen/mandarin/zh_sandhi.py
wunsen/mandarin/zh_splitter.py
wunsen/mandarin/zh_thapsap.py
wunsen/splitutils/__init__.py
wunsen/splitutils/exception.py
wunsen/splitutils/splitter.py
wunsen/vietnamese/__init__.py
wunsen/vietnamese/vi_mapping.py
wunsen/vietnamese/vi_splitter.py
wunsen/vietnamese/vi_thapsap.py
wunsen-0.0.3.dist-info/METADATA
wunsen-0.0.3.dist-info/WHEEL
wunsen-0.0.3.dist-info/licenses/LICENSE
wunsen-0.0.3.dist-info/RECORD
