Metadata-Version: 2.1
Name: wunsen
Version: 0.0.3
Summary: Transliterate/transcribe from other languages into Thai
Project-URL: Homepage, https://github.com/cakimpei/wunsen
Project-URL: Bug Tracker, https://github.com/cakimpei/wunsen/issues
Author-email: cakimpei <cakimpei@gmail.com>
License: MIT License
Classifier: License :: OSI Approved :: MIT License
Classifier: Operating System :: OS Independent
Classifier: Programming Language :: Python :: 3
Requires-Python: >=3.7
Requires-Dist: khanaa>=0.0.6
